Metadata-Version: 1.0
Name: chatbase
Version: 0.2
Summary: Python module for interacting with Chatbase APIs
Home-page: https://chatbase.com/documentation
Author: Google Inc.
Author-email: chatbase-feedback@google.com
License: Apache-2.0
Platform: UNKNOWN
